warframe/worldstate/__init__.py
warframe/worldstate/client.py
warframe/worldstate/endpoints.py
warframe/worldstate/exceptions.py
warframe/worldstate/listeners.py
warframe/worldstate/utils.py
warframe/worldstate/common/__init__.py
warframe/worldstate/common/core.py
warframe/worldstate/common/logger.py
warframe/worldstate/common/types_.py
warframe/worldstate/enums/__init__.py
warframe/worldstate/enums/faction.py
warframe/worldstate/enums/language.py
warframe/worldstate/enums/mission_type.py
warframe/worldstate/enums/syndicate.py
warframe/worldstate/models/__init__.py
warframe/worldstate/models/alert.py
warframe/worldstate/models/arbitration.py
warframe/worldstate/models/archon_hunt.py
warframe/worldstate/models/cambion_drift.py
warframe/worldstate/models/cetus.py
warframe/worldstate/models/counted_item.py
warframe/worldstate/models/daily_deal.py
warframe/worldstate/models/event.py
warframe/worldstate/models/fissure.py
warframe/worldstate/models/flash_sale.py
warframe/worldstate/models/invasion.py
warframe/worldstate/models/mission.py
warframe/worldstate/models/orb_vallis.py
warframe/worldstate/models/reward.py
warframe/worldstate/models/sortie.py
warframe/worldstate/models/void_trader.py
warframe.py-1.1.0.dist-info/LICENSE
warframe.py-1.1.0.dist-info/METADATA
warframe.py-1.1.0.dist-info/WHEEL
warframe.py-1.1.0.dist-info/top_level.txt
warframe.py-1.1.0.dist-info/RECORD
